{
  "type": "Item",
  "folder": "bBDJDqsshLIbQDyE",
  "name": "Expert",
  "color": null,
  "sorting": "a",
  "_id": "GaSIkEMI2Yi6RoKu",
  "description": "",
  "sort": 200000,
  "flags": {
    "scene-packer": {
      "hash": "c4206d8dda5b0a5d6de67ee95abe983ec2601f3e"
    }
  },
  "_stats": {
    "compendiumSource": null,
    "duplicateSource": null,
    "exportSource": null,
    "coreVersion": "13.351",
    "systemId": "redsteel",
    "systemVersion": "0.8.1",
    "lastModifiedBy": null
  },
  "_key": "!folders!GaSIkEMI2Yi6RoKu"
}
